{
  "version": "1.3.2",
  "notes": "v1.3.2 — UI: кнопки хедера, переключение каналов→чаты, весь интерфейс на русском",
  "pub_date": "2026-04-09T00:00:00Z",
  "platforms": {
    "windows-x86_64": {
      "url": "https://github.com/r2bb1tDev/Soviet/releases/download/v1.3.2/Soviet_1.3.2_x64-setup.exe",
      "signature": ""
    },
    "darwin-aarch64": {
      "url": "https://github.com/r2bb1tDev/Soviet/releases/download/v1.3.2/Soviet_1.3.2_aarch64.dmg",
      "signature": ""
    },
    "darwin-x86_64": {
      "url": "https://github.com/r2bb1tDev/Soviet/releases/download/v1.3.2/Soviet_1.3.2_x64.dmg",
      "signature": ""
    },
    "linux-x86_64": {
      "url": "https://github.com/r2bb1tDev/Soviet/releases/download/v1.3.2/Soviet_1.3.2_amd64.AppImage",
      "signature": ""
    }
  }
}
